hdpitkinter.py
hdpitkinter-2.0.1.dist-info/METADATA
hdpitkinter-2.0.1.dist-info/WHEEL
hdpitkinter-2.0.1.dist-info/top_level.txt
hdpitkinter-2.0.1.dist-info/RECORD
