Metadata-Version: 2.4
Name: hdpitkinter
Version: 2.0.1
Summary: Meta-package: hdpitkinter has been renamed to tkinter-unblur
Author: unlibra
License: MIT
Project-URL: Homepage, https://github.com/unlibra/tkinter-unblur
Project-URL: Migrated to, https://pypi.org/project/tkinter-unblur/
Project-URL: Repository, https://github.com/unlibra/tkinter-unblur
Keywords: tkinter,dpi,hdpi,deprecated,renamed
Classifier: Development Status :: 7 - Inactive
Classifier: Intended Audience :: Developers
Classifier: License :: OSI Approved :: MIT License
Classifier: Operating System :: Microsoft :: Windows
Classifier: Operating System :: OS Independent
Classifier: Programming Language :: Python :: 3
Classifier: Programming Language :: Python :: 3.9
Classifier: Programming Language :: Python :: 3.10
Classifier: Programming Language :: Python :: 3.11
Classifier: Programming Language :: Python :: 3.12
Classifier: Programming Language :: Python :: 3.13
Classifier: Programming Language :: Python :: 3.14
Requires-Python: >=3.9
Requires-Dist: tkinter-unblur>=1.0.0
